<?xml version="1.0" encoding="UTF-8"?>
<objects serializationModel="Studio.02.02.00">
	<object class="AudioFile" id="{ffee88ab-0de6-4c5a-9d6a-bc4236101787}">
		<property name="assetPath">
			<value>enemy barks/balloon cluster enemy barks/taunt/balloon cluster We got numbers on our side.wav</value>
		</property>
		<property name="frequencyInKHz">
			<value>48</value>
		</property>
		<property name="channelCount">
			<value>1</value>
		</property>
		<property name="length">
			<value>2.2338541666666667</value>
		</property>
		<relationship name="masterAssetFolder">
			<destination>{4310d54c-e4ea-4d34-8a1d-8701c9e2c25d}</destination>
		</relationship>
	</object>
</objects>
